signia/__init__.py
signia/_core.py
signia/py.typed
signia-0.1.1.dist-info/METADATA
signia-0.1.1.dist-info/WHEEL
signia-0.1.1.dist-info/top_level.txt
signia-0.1.1.dist-info/RECORD
