Metadata-Version: 2.4
Name: signia
Version: 0.1.1
Summary: Function Signature Tools
Author: Tim Marquart
Requires-Python: >=3.9
